{"URL": "https://mbasic.facebook.com/story.php?story_fbid=2392214850922387&id=606218229522067&refid=17&_ft_=mf_story_key.2392214850922387%3Atop_level_post_id.2392214850922387%3Atl_objid.2392214850922387%3Acontent_owner_id_new.606218229522067%3Athrowback_story_fbid.2392214850922387%3Apage_id.606218229522067%3Astory_location.4%3Astory_attachment_style.photo%3Atds_flgs.3%3Aott.AX-Pdrssoqwum4Ef%3Athid.606218229522067%3A306061129499414%3A2%3A0%3A1622530799%3A-3883614356526393244&__tn__=%2As-R", "PUBLISHER": "taiwanheadbrewers", "CONTENT": "查看編輯紀錄啤酒頭 Taiwan Head Brewers Brewing Company【2021 小滿】​ ​ 過去這星期，對每個人而言都是難熬的一週。​ ​ 所有見面的活動戛然而止，店家忙著轉變經營模式。一瞬間，工作轉為線上，學校轉為線上，連品飲會也線上進行。我們來不及一起喝一杯，也來不及面對面說再見。​ ​ 難關終究會過去，殷殷期盼在陽光下一起喝啤酒的日子。​ ​ 節氣「小滿者，物至於此小得盈滿。」指的是夏熟作物逐漸長大趨於飽滿，對於農家來說，「小滿」代表著對於未來莊稼豐收的殷殷期盼。​ ​ 願每個人都平安。 🙏🏻🙏🏻🙏🏻​ ​ ​ [請理性飲酒，喝酒不開車]​ ​ ​ ＃小滿宅家陪你喝​ ＃減少不必要的外出5月21日下午7:00 · ", "SENTENCE": ["查看編輯紀錄啤酒頭 Taiwan Head Brewers Brewing Company【2021 小滿】​ ​ 過去這星期", "對每個人而言都是難熬的一週", "​ ​ 所有見面的活動戛然而止", "店家忙著轉變經營模式", "一瞬間", "工作轉為線上", "學校轉為線上", "連品飲會也線上進行", "我們來不及一起喝一杯", "也來不及面對面說再見", "​ ​ 難關終究會過去", "殷殷期盼在陽光下一起喝啤酒的日子", "​ ​ 節氣「小滿者", "物至於此小得盈滿", "」指的是夏熟作物逐漸長大趨於飽滿", "對於農家來說", "「小滿」代表著對於未來莊稼豐收的殷殷期盼", "​ ​ 願每個人都平安", " 🙏🏻🙏🏻🙏🏻​ ​ ​ [請理性飲酒", "喝酒不開車]​ ​ ​ ＃小滿宅家陪你喝​ ＃減少不必要的外出5月21日下午7:00 ", " "], "WORDS": [[" ", 23], ["​", 15], ["，", 11], ["。", 8], ["的", 6], ["小滿", 4], ["線上", 3], ["過去", 2], ["每個", 2], ["人", 2], ["都", 2], ["是", 2], ["轉為", 2], ["會", 2], ["也", 2], ["來不及", 2], ["一起", 2], ["喝", 2], ["說", 2], ["期盼", 2], ["「", 2], ["」", 2], ["對於", 2], ["殷", 2], ["不", 2], ["＃", 2], ["查看", 1], ["編輯", 1], ["紀錄", 1], ["啤酒頭", 1], [" Taiwan", 1], ["Head", 1], ["Brewers", 1], ["Brewing", 1], ["Company", 1], ["【", 1], ["2021 ", 1], ["】", 1], ["這星期", 1], ["對", 1], ["而", 1], ["言", 1], ["難熬", 1], ["一週", 1], ["所有", 1], ["見面", 1], ["活動", 1], ["戛", 1], ["然而", 1], ["止", 1], ["店家", 1], ["忙著", 1], ["轉變", 1], ["經營模式", 1], ["一瞬間", 1], ["工作", 1], ["學校", 1], ["連", 1], ["品飲", 1], ["進行", 1], ["我們", 1], ["一杯", 1], ["面對面", 1], ["再見", 1], ["難關", 1], ["終究", 1], ["殷殷", 1], ["在", 1], ["陽光", 1], ["下", 1], ["啤酒", 1], ["日子", 1], ["節氣", 1], ["者", 1], ["物", 1], ["至於", 1], ["此", 1], ["小", 1], ["得盈", 1], ["滿", 1], ["指", 1], ["夏", 1], ["熟", 1], ["作物", 1], ["逐漸", 1], ["長大", 1], ["趨於", 1], ["飽滿", 1], ["農家", 1], ["來", 1], ["代表著", 1], ["未來", 1], ["莊稼", 1], ["豐收", 1], ["願", 1], ["平安", 1], ["🙏🏻🙏🏻🙏🏻​", 1], ["[", 1], ["請", 1], ["理性", 1], ["飲酒", 1], ["喝酒", 1], ["開車", 1], ["]", 1], ["宅家", 1], ["陪", 1], ["你", 1], ["喝​", 1], ["減少", 1], ["必要", 1], ["外出", 1], ["5月", 1], ["21日", 1], ["下午", 1], ["7", 1], [":", 1], ["00 ", 1], ["·", 1]]}